Strava_API/Strava_API.py
Strava_API/__init__.py
StravaSocialAPI-1.0.2.dist-info/LICENSE.txt
StravaSocialAPI-1.0.2.dist-info/METADATA
StravaSocialAPI-1.0.2.dist-info/WHEEL
StravaSocialAPI-1.0.2.dist-info/top_level.txt
StravaSocialAPI-1.0.2.dist-info/RECORD
