Metadata-Version: 2.1
Name: StravaSocialAPI
Version: 1.0.2
Summary: API fro Strava that interacts with the social media
Author: Tom
License-File: LICENSE.txt
Requires-Dist: selenium
